dbsink/__init__.py
dbsink/listen.py
dbsink/maps.py
dbsink/tables.py
dbsink/utils.py
dbsink-2.6.0.dist-info/LICENSE.txt
dbsink-2.6.0.dist-info/METADATA
dbsink-2.6.0.dist-info/WHEEL
dbsink-2.6.0.dist-info/entry_points.txt
dbsink-2.6.0.dist-info/top_level.txt
dbsink-2.6.0.dist-info/zip-safe
dbsink-2.6.0.dist-info/RECORD
