Metadata-Version: 2.1
Name: dbsink
Version: 2.6.0
Summary: Tools to sink kafka messages to a database table
Home-page: https://github.com/axiom-data-science/dbsink
Author: Kyle Wilcox
Author-email: kyle@axds.co
License: MIT
Platform: UNKNOWN
Classifier: Development Status :: 5 - Production/Stable
Classifier: Intended Audience :: Science/Research
Classifier: Operating System :: OS Independent
Classifier: License :: OSI Approved :: MIT License
Classifier: Programming Language :: Python
Classifier: Programming Language :: Python :: 3
Classifier: Programming Language :: Python :: 3.7
Classifier: Programming Language :: Python :: 3.8
Classifier: Topic :: Scientific/Engineering
Requires-Python: >=3.7
Requires-Dist: click
Requires-Dist: easyavro (>=3.0.0)
Requires-Dist: geoalchemy2
Requires-Dist: msgpack-python
Requires-Dist: psycopg2
Requires-Dist: python-dateutil
Requires-Dist: pytz
Requires-Dist: shapely
Requires-Dist: simplejson
Requires-Dist: sqlalchemy
